easy_scpi/__about__.py
easy_scpi/__init__.py
easy_scpi/scpi_instrument.py
easy_scpi-0.1.6.dist-info/METADATA
easy_scpi-0.1.6.dist-info/WHEEL
easy_scpi-0.1.6.dist-info/licenses/LICENSE-APACHE
easy_scpi-0.1.6.dist-info/licenses/LICENSE-MIT
easy_scpi-0.1.6.dist-info/RECORD
