Metadata-Version: 2.3
Name: easy-scpi
Version: 0.1.6
Summary: An easy library for controlling SCPI instruments.
Project-URL: Issues, https://github.com/bicarlsen/easy-scpi/issues
Project-URL: Source, https://github.com/bicarlsen/easy-scpi
Project-URL: Homepage, https://github.com/bicarlsen/easy-scpi
Author-email: Brian Carlsen <carlsen.bri@gmail.com>
License: MIT OR Apache-2.0
Keywords: scpi
Classifier: License :: OSI Approved :: Apache Software License
Classifier: License :: OSI Approved :: MIT License
Classifier: Operating System :: OS Independent
Classifier: Programming Language :: Python :: 3
Requires-Dist: pyvisa
